{
    "page_number": 468,
    "data": [
        {
            "aya_id": 4141,
            "aya_number": 8,
            "aya_text": "رَبَّنَا وَاَدْخِلْهُمْ جَنّٰتِ عَدْنِ ِۨالَّتِيْ وَعَدْتَّهُمْ وَمَنْ صَلَحَ مِنْ اٰبَاۤىِٕهِمْ وَاَزْوَاجِهِمْ وَذُرِّيّٰتِهِمْ ۗاِنَّكَ اَنْتَ الْعَزِيْزُ الْحَكِيْمُۙ ",
            "sura_id": 40,
            "juz_id": 24,
            "page_number": 468,
            "translation_aya_text": "Ya Tuhan kami, masukkanlah mereka ke dalam surga ‘Adn yang telah Engkau janjikan kepada mereka, dan orang yang saleh di antara nenek moyang mereka, istri-istri, dan keturunan mereka. Sungguh, Engkaulah Yang Mahaperkasa, Mahabijaksana,",
            "tafsir_jalalayn": "(Ya Rabb kami! Masukkanlah mereka ke dalam surga Adn) sebagai tempat tinggal mereka (yang telah Engkau janjikan kepada mereka dan orang-orang yang saleh) lafal Man shalaha diathafkan kepada lafal Hum yang terdapat di dalam lafal Wa-adkhilhum atau yang terdapat pada lafal Wa'adtahum (dari bapak-bapak mereka, dan istri-istri mereka, dan keturunan mereka. Sesungguhnya Engkaulah Yang Maha Perkasa lagi Maha Bijaksana) di dalam perbuatan-Nya.",
            "sajda": false,
            "transliteration": "Rabbannaa wa adkhilhum Jannaati 'adninil latee wa'attahum wa man salaha min aabaaa'ihim wa azwaajihim wa zurriyyaatihim; innaka Antal 'Azeezul Hakeem",
            "tajweed_text": "رَبَّنَا وَأَ[q:11781[دْ]خِلْهُمْ جَ[g[نّ]َ[n[ـٰ]تِ عَ[q:5720[دْ]نٍ [h:8376[ٱ]لَّتِى وَعَ[d:11782[د]تَّهُمْ وَمَ[f:6964[ن ص]َلَحَ مِنْ ءَاب[o[َا]ٓئِهِمْ وَأَزْو[n[َٲ]جِهِمْ وَذُرِّيَّ[n[ـٰ]تِهِمْۚ إِ[g[نّ]َكَ أَ[f:169[نت]َ [h:680[ٱ]لْعَزِيزُ [h:681[ٱ]لْحَك[p[ِي]مُ",
            "words": [
                {
                    "position": 1,
                    "arabic": "رَبَّنَا",
                    "transliteration": "rabbanā",
                    "translation": "Our Lord",
                    "analysis_id": 1775
                },
                {
                    "position": 2,
                    "arabic": "وَاَدْخِلْهُمْ",
                    "transliteration": "wa-adkhil'hum",
                    "translation": "And admit them",
                    "analysis_id": 24301
                },
                {
                    "position": 3,
                    "arabic": "جَنّٰتِ",
                    "transliteration": "jannāti",
                    "translation": "(to) Gardens",
                    "analysis_id": 9231
                },
                {
                    "position": 4,
                    "arabic": "عَدْنِ",
                    "transliteration": "ʿadnin",
                    "translation": "(of) Eden",
                    "analysis_id": 13308
                },
                {
                    "position": 5,
                    "arabic": "ِۨالَّتِيْ",
                    "transliteration": "allatī",
                    "translation": "which",
                    "analysis_id": 18537
                },
                {
                    "position": 6,
                    "arabic": "وَعَدْتَّهُمْ",
                    "transliteration": "waʿadttahum",
                    "translation": "You have promised them",
                    "analysis_id": 24302
                },
                {
                    "position": 7,
                    "arabic": "وَمَنْ",
                    "transliteration": "waman",
                    "translation": "and whoever",
                    "analysis_id": 4698
                },
                {
                    "position": 8,
                    "arabic": "صَلَحَ",
                    "transliteration": "ṣalaḥa",
                    "translation": "(was) righteous",
                    "analysis_id": 15917
                },
                {
                    "position": 9,
                    "arabic": "مِنْ",
                    "transliteration": "min",
                    "translation": "among",
                    "analysis_id": 53
                },
                {
                    "position": 10,
                    "arabic": "اٰبَاۤىِٕهِمْ",
                    "transliteration": "ābāihim",
                    "translation": "their fathers",
                    "analysis_id": 10332
                },
                {
                    "position": 11,
                    "arabic": "وَاَزْوَاجِهِمْ",
                    "transliteration": "wa-azwājihim",
                    "translation": "and their spouses",
                    "analysis_id": 15918
                },
                {
                    "position": 12,
                    "arabic": "وَذُرِّيّٰتِهِمْ",
                    "transliteration": "wadhurriyyātihim",
                    "translation": "and their offspring",
                    "analysis_id": 10333
                },
                {
                    "position": 13,
                    "arabic": "ۗاِنَّكَ",
                    "transliteration": "innaka",
                    "translation": "Indeed You",
                    "analysis_id": 471
                },
                {
                    "position": 14,
                    "arabic": "اَنْتَ",
                    "transliteration": "anta",
                    "translation": "You",
                    "analysis_id": 472
                },
                {
                    "position": 15,
                    "arabic": "الْعَزِيْزُ",
                    "transliteration": "l-ʿazīzu",
                    "translation": "(are) the All-Mighty",
                    "analysis_id": 9697
                },
                {
                    "position": 16,
                    "arabic": "الْحَكِيْمُۙ",
                    "transliteration": "l-ḥakīmu",
                    "translation": "the All-Wise",
                    "analysis_id": 24303
                }
            ]
        },
        {
            "aya_id": 4142,
            "aya_number": 9,
            "aya_text": "وَقِهِمُ السَّيِّاٰتِۗ وَمَنْ تَقِ السَّيِّاٰتِ يَوْمَىِٕذٍ فَقَدْ رَحِمْتَهٗ ۗوَذٰلِكَ هُوَ الْفَوْزُ الْعَظِيْمُ ࣖ ",
            "sura_id": 40,
            "juz_id": 24,
            "page_number": 468,
            "translation_aya_text": "dan peliharalah mereka dari (bencana) kejahatan. Dan orang-orang yang Engkau pelihara dari (bencana) kejahatan pada hari itu, maka sungguh, Engkau telah menganugerahkan rahmat kepadanya dan demikian itulah kemenangan yang agung.”",
            "tafsir_jalalayn": "(Dan peliharalah mereka dari kejahatan) dari balasan azabnya (Dan orang-orang yang Engkau pelihara dari balasan kejahatan pada hari itu) pada hari kiamat (maka sesungguhnya telah Engkau anugerahkan rahmat kepadanya dan itulah kemenangan yang besar.\")",
            "sajda": false,
            "transliteration": "Wa qihimus saiyi-aat; wa man taqis saiyi-aati Yawma'izin faqad rahimtah; wa zaalika huwal fawzul 'azeem",
            "tajweed_text": "وَقِهِمُ [h:11783[ٱ][l[ل]سَّيِّـَٔـاتِۚ وَمَ[f:11784[ن ت]َقِ [h:11785[ٱ][l[ل]سَّيِّـَٔـاتِ يَوْمَئِ[f:3960[ذٍ ف]َقَ[q:563[دْ] رَحِمْتَهُ[n[ۥ]ۚ وَذ[n[َٲ]لِكَ هُوَ [h:5722[ٱ]لْفَوْزُ [h:2633[ٱ]لْعَظ[p[ِي]مُ",
            "words": [
                {
                    "position": 1,
                    "arabic": "وَقِهِمُ",
                    "transliteration": "waqihimu",
                    "translation": "And protect them",
                    "analysis_id": 24300
                },
                {
                    "position": 2,
                    "arabic": "السَّيِّاٰتِۗ",
                    "transliteration": "l-sayiāti",
                    "translation": "(from) the evils",
                    "analysis_id": 6752
                },
                {
                    "position": 3,
                    "arabic": "وَمَنْ",
                    "transliteration": "waman",
                    "translation": "And whoever",
                    "analysis_id": 3750
                },
                {
                    "position": 4,
                    "arabic": "تَقِ",
                    "transliteration": "taqi",
                    "translation": "you protect",
                    "analysis_id": 24304
                },
                {
                    "position": 5,
                    "arabic": "السَّيِّاٰتِ",
                    "transliteration": "l-sayiāti",
                    "translation": "(from) the evils",
                    "analysis_id": 11939
                },
                {
                    "position": 6,
                    "arabic": "يَوْمَىِٕذٍ",
                    "transliteration": "yawma-idhin",
                    "translation": "that Day",
                    "analysis_id": 7091
                },
                {
                    "position": 7,
                    "arabic": "فَقَدْ",
                    "transliteration": "faqad",
                    "translation": "then verily",
                    "analysis_id": 1535
                },
                {
                    "position": 8,
                    "arabic": "رَحِمْتَهٗ",
                    "transliteration": "raḥim'tahu",
                    "translation": "You have bestowed mercy on him",
                    "analysis_id": 24305
                },
                {
                    "position": 9,
                    "arabic": "ۗوَذٰلِكَ",
                    "transliteration": "wadhālika",
                    "translation": "And that",
                    "analysis_id": 13594
                },
                {
                    "position": 10,
                    "arabic": "هُوَ",
                    "transliteration": "huwa",
                    "translation": "[it]",
                    "analysis_id": 408
                },
                {
                    "position": 11,
                    "arabic": "الْفَوْزُ",
                    "transliteration": "l-fawzu",
                    "translation": "(is) the success",
                    "analysis_id": 9813
                },
                {
                    "position": 12,
                    "arabic": "الْعَظِيْمُ",
                    "transliteration": "l-ʿaẓīmu",
                    "translation": "the great",
                    "analysis_id": 13238
                },
                {
                    "position": 13,
                    "arabic": "ࣖ",
                    "transliteration": null,
                    "translation": "(9)",
                    "analysis_id": 31
                }
            ]
        },
        {
            "aya_id": 4143,
            "aya_number": 10,
            "aya_text": "اِنَّ الَّذِيْنَ كَفَرُوْا يُنَادَوْنَ لَمَقْتُ اللّٰهِ اَكْبَرُ مِنْ مَّقْتِكُمْ اَنْفُسَكُمْ اِذْ تُدْعَوْنَ اِلَى الْاِيْمَانِ فَتَكْفُرُوْنَ",
            "sura_id": 40,
            "juz_id": 24,
            "page_number": 468,
            "translation_aya_text": "Sesungguhnya orang-orang yang kafir, kepada mereka (pada hari Kiamat) diserukan, “Sungguh, kebencian Allah (kepadamu) jauh lebih besar daripada kebencianmu kepada dirimu sendiri, ketika kamu diseru untuk beriman lalu kamu mengingkarinya.”",
            "tafsir_jalalayn": "(Sesungguhnya orang-orang yang kafir diserukan kepada mereka) oleh para malaikat, sedangkan mereka membenci diri mereka sendiri sewaktu mereka dimasukkan ke dalam neraka (\"Sesungguhnya kebencian Allah) kepada kalian (lebih besar daripada kebencian kalian kepada diri kalian sendiri karena kalian diseru) sewaktu di dunia (untuk beriman, lalu kalian kafir.\")",
            "sajda": false,
            "transliteration": "Innal lazeena kafaroo yunaadawna lamaqtul laahi akbaru mim maqtikum anfusakum iz tud'awna ilal eemaani fatakfuroon",
            "tajweed_text": "إِ[g[نّ]َ [h:24[ٱ]لَّذِينَ كَفَرُو[s[اْ] يُنَادَوْنَ لَمَ[q:11786[قْ]تُ [h:11787[ٱ]للَّهِ أَكْبَرُ م[a:11788[ِن م]َّ[q:11789[قْ]تِكُمْ أَ[f:221[نف]ُسَكُمْ إِذْ تُ[q:11790[دْ]عَوْنَ إِلَى [h:11791[ٱ]لْإِيمَ[n[ـٰ]نِ فَتَكْفُر[p[ُو]نَ",
            "words": [
                {
                    "position": 1,
                    "arabic": "اِنَّ",
                    "transliteration": "inna",
                    "translation": "Indeed",
                    "analysis_id": 66
                },
                {
                    "position": 2,
                    "arabic": "الَّذِيْنَ",
                    "transliteration": "alladhīna",
                    "translation": "those who",
                    "analysis_id": 22
                },
                {
                    "position": 3,
                    "arabic": "كَفَرُوْا",
                    "transliteration": "kafarū",
                    "translation": "disbelieved",
                    "analysis_id": 67
                },
                {
                    "position": 4,
                    "arabic": "يُنَادَوْنَ",
                    "transliteration": "yunādawna",
                    "translation": "will be cried out to them",
                    "analysis_id": 24306
                },
                {
                    "position": 5,
                    "arabic": "لَمَقْتُ",
                    "transliteration": "lamaqtu",
                    "translation": "Certainly Allah's hatred",
                    "analysis_id": 24307
                },
                {
                    "position": 6,
                    "arabic": "اللّٰهِ",
                    "transliteration": "l-lahi",
                    "translation": "Certainly Allah's hatred",
                    "analysis_id": 2
                },
                {
                    "position": 7,
                    "arabic": "اَكْبَرُ",
                    "transliteration": "akbaru",
                    "translation": "(was) greater",
                    "analysis_id": 13310
                },
                {
                    "position": 8,
                    "arabic": "مِنْ",
                    "transliteration": "min",
                    "translation": "than",
                    "analysis_id": 53
                },
                {
                    "position": 9,
                    "arabic": "مَّقْتِكُمْ",
                    "transliteration": "maqtikum",
                    "translation": "your hatred",
                    "analysis_id": 24308
                },
                {
                    "position": 10,
                    "arabic": "اَنْفُسَكُمْ",
                    "transliteration": "anfusakum",
                    "translation": "(of) yourselves",
                    "analysis_id": 703
                },
                {
                    "position": 11,
                    "arabic": "اِذْ",
                    "transliteration": "idh",
                    "translation": "when",
                    "analysis_id": 1814
                },
                {
                    "position": 12,
                    "arabic": "تُدْعَوْنَ",
                    "transliteration": "tud'ʿawna",
                    "translation": "you were called",
                    "analysis_id": 24309
                },
                {
                    "position": 13,
                    "arabic": "اِلَى",
                    "transliteration": "ilā",
                    "translation": "to",
                    "analysis_id": 417
                },
                {
                    "position": 14,
                    "arabic": "الْاِيْمَانِ",
                    "transliteration": "l-īmāni",
                    "translation": "the faith",
                    "analysis_id": 24310
                },
                {
                    "position": 15,
                    "arabic": "فَتَكْفُرُوْنَ",
                    "transliteration": "fatakfurūna",
                    "translation": "and you disbelieved",
                    "analysis_id": 24311
                }
            ]
        },
        {
            "aya_id": 4144,
            "aya_number": 11,
            "aya_text": "قَالُوْا رَبَّنَآ اَمَتَّنَا اثْنَتَيْنِ وَاَحْيَيْتَنَا اثْنَتَيْنِ فَاعْتَرَفْنَا بِذُنُوْبِنَا فَهَلْ اِلٰى خُرُوْجٍ مِّنْ سَبِيْلٍ",
            "sura_id": 40,
            "juz_id": 24,
            "page_number": 468,
            "translation_aya_text": "Mereka menjawab, “Ya Tuhan kami, Engkau telah mematikan kami dua kali dan telah menghidupkan kami dua kali (pula), lalu kami mengakui dosa-dosa kami. Maka adakah jalan (bagi kami) untuk keluar (dari neraka)?”",
            "tafsir_jalalayn": "(Mereka menjawab, \"Ya Rabb kami, Engkau telah mematikan kami dua kali) yakni dua kali mati (dan telah menghidupkan kami dua kali pula) yakni dua kali hidup. Karena sesungguhnya sebelum itu mereka berupa mani, dalam keadaan mati, kemudian mereka dijadikan hidup, lalu mereka dimatikan lagi, lalu mereka dihidupkan lagi pada hari berbangkit (lalu kami mengakui dosa-dosa kami) yaitu dosa keingkaran kami terhadap adanya hari berbangkit. (Maka adakah untuk keluar) dari neraka lalu kembali lagi ke dunia, supaya kami dapat menjalani ketaatan kepada Rabb kami (sesuatu jalan\") yakni jalan keluar, maka jawaban mereka adalah tidak ada.",
            "sajda": false,
            "transliteration": "Qaaloo Rabbanaaa amat tanasnataini wa ahyaitanas nataini fa'tarafnaa bizunoo binaa fahal ilaa khuroojim min sabeel",
            "tajweed_text": "قَالُو[s[اْ] رَبَّن[o[َآ] أَمَتَّنَا [h:11792[ٱ]ثْنَتَيْنِ وَأَحْيَيْتَنَا [h:11793[ٱ]ثْنَتَيْنِ فَ[h:11794[ٱ]عْتَرَفْنَا بِذُنُوبِنَا فَهَلْ إِلَىٰ خُرُو[a:11795[جٍ م]ِّ[f:5782[ن س]َب[p[ِي]لٍ",
            "words": [
                {
                    "position": 1,
                    "arabic": "قَالُوْا",
                    "transliteration": "qālū",
                    "translation": "They (will) say",
                    "analysis_id": 465
                },
                {
                    "position": 2,
                    "arabic": "رَبَّنَآ",
                    "transliteration": "rabbanā",
                    "translation": "Our Lord",
                    "analysis_id": 2850
                },
                {
                    "position": 3,
                    "arabic": "اَمَتَّنَا",
                    "transliteration": "amattanā",
                    "translation": "You gave us death",
                    "analysis_id": 24312
                },
                {
                    "position": 4,
                    "arabic": "اثْنَتَيْنِ",
                    "transliteration": "ith'natayni",
                    "translation": "twice",
                    "analysis_id": 24313
                },
                {
                    "position": 5,
                    "arabic": "وَاَحْيَيْتَنَا",
                    "transliteration": "wa-aḥyaytanā",
                    "translation": "and You gave us life",
                    "analysis_id": 24314
                },
                {
                    "position": 6,
                    "arabic": "اثْنَتَيْنِ",
                    "transliteration": "ith'natayni",
                    "translation": "twice",
                    "analysis_id": 24313
                },
                {
                    "position": 7,
                    "arabic": "فَاعْتَرَفْنَا",
                    "transliteration": "fa-iʿ'tarafnā",
                    "translation": "and we confess",
                    "analysis_id": 24315
                },
                {
                    "position": 8,
                    "arabic": "بِذُنُوْبِنَا",
                    "transliteration": "bidhunūbinā",
                    "translation": "our sins",
                    "analysis_id": 24316
                },
                {
                    "position": 9,
                    "arabic": "فَهَلْ",
                    "transliteration": "fahal",
                    "translation": "So is (there)",
                    "analysis_id": 9436
                },
                {
                    "position": 10,
                    "arabic": "اِلٰى",
                    "transliteration": "ilā",
                    "translation": "to",
                    "analysis_id": 706
                },
                {
                    "position": 11,
                    "arabic": "خُرُوْجٍ",
                    "transliteration": "khurūjin",
                    "translation": "get out",
                    "analysis_id": 24317
                },
                {
                    "position": 12,
                    "arabic": "مِّنْ",
                    "transliteration": "min",
                    "translation": "any",
                    "analysis_id": 53
                },
                {
                    "position": 13,
                    "arabic": "سَبِيْلٍ",
                    "transliteration": "sabīlin",
                    "translation": "way",
                    "analysis_id": 7101
                }
            ]
        },
        {
            "aya_id": 4145,
            "aya_number": 12,
            "aya_text": "ذٰلِكُمْ بِاَنَّهٗٓ اِذَا دُعِيَ اللّٰهُ وَحْدَهٗ كَفَرْتُمْۚ وَاِنْ يُّشْرَكْ بِهٖ تُؤْمِنُوْا ۗفَالْحُكْمُ لِلّٰهِ الْعَلِيِّ الْكَبِيْرِ",
            "sura_id": 40,
            "juz_id": 24,
            "page_number": 468,
            "translation_aya_text": "Yang demikian itu karena sesungguhnya kamu mengingkari apabila diseru untuk menyembah Allah saja. Dan jika Allah dipersekutukan, kamu percaya. Maka keputusan (sekarang ini) adalah pada Allah Yang Mahatinggi, Mahabesar.",
            "tafsir_jalalayn": "(Yang demikian itu) maksudnya, azab yang kalian sedang jalani itu (adalah karena) ketika di dunia (kalian kafir apabila Allah saja disembah) artinya, kalian kafir bilamana Dia diesakan. (Dan apabila Allah dipersekutukan) menjadikan sekutu bagi-Nya (kalian percaya) kalian percaya kepada kemusyrikan itu. (Maka putusan) untuk mengazab kalian (adalah pada Allah Yang Maha Tinggi) atas semua makhluk-Nya (lagi Maha Besar) Maha Agung.",
            "sajda": false,
            "transliteration": "Zaalikum bi annahooo izaa du'iyal laahu wahdahoo kafartum wa iny yushrak bihee tu'minoo; falhukmu lillaahil 'Aliyyil Kabeer",
            "tajweed_text": "ذ[n[َٲ]لِك[c:11796[ُم ب]ِأَ[g[نّ]َهُ[o[ۥٓ] إِذَا دُعِىَ [h:11797[ٱ]للَّهُ وَحْدَهُ[n[ۥ] كَفَرْتُمْۖ وَإ[a:11798[ِن ي]ُشْرَكْ بِه[n[ِۦ] تُؤْمِنُو[s[اْۚ] فَ[h:11799[ٱ]لْحُكْمُ لِلَّهِ [h:11800[ٱ]لْعَلِىِّ [h:11801[ٱ]لْكَب[p[ِي]رِ",
            "words": [
                {
                    "position": 1,
                    "arabic": "ذٰلِكُمْ",
                    "transliteration": "dhālikum",
                    "translation": "That",
                    "analysis_id": 710
                },
                {
                    "position": 2,
                    "arabic": "بِاَنَّهٗٓ",
                    "transliteration": "bi-annahu",
                    "translation": "(is) because",
                    "analysis_id": 24318
                },
                {
                    "position": 3,
                    "arabic": "اِذَا",
                    "transliteration": "idhā",
                    "translation": "when",
                    "analysis_id": 2450
                },
                {
                    "position": 4,
                    "arabic": "دُعِيَ",
                    "transliteration": "duʿiya",
                    "translation": "Allah was invoked",
                    "analysis_id": 24319
                },
                {
                    "position": 5,
                    "arabic": "اللّٰهُ",
                    "transliteration": "l-lahu",
                    "translation": "Allah was invoked",
                    "analysis_id": 75
                },
                {
                    "position": 6,
                    "arabic": "وَحْدَهٗ",
                    "transliteration": "waḥdahu",
                    "translation": "Alone",
                    "analysis_id": 11443
                },
                {
                    "position": 7,
                    "arabic": "كَفَرْتُمْۚ",
                    "transliteration": "kafartum",
                    "translation": "you disbelieved",
                    "analysis_id": 17435
                },
                {
                    "position": 8,
                    "arabic": "وَاِنْ",
                    "transliteration": "wa-in",
                    "translation": "but if",
                    "analysis_id": 3278
                },
                {
                    "position": 9,
                    "arabic": "يُّشْرَكْ",
                    "transliteration": "yush'rak",
                    "translation": "(others) were associated",
                    "analysis_id": 24320
                },
                {
                    "position": 10,
                    "arabic": "بِهٖ",
                    "transliteration": "bihi",
                    "translation": "with Him",
                    "analysis_id": 375
                },
                {
                    "position": 11,
                    "arabic": "تُؤْمِنُوْا",
                    "transliteration": "tu'minū",
                    "translation": "you believed",
                    "analysis_id": 24321
                },
                {
                    "position": 12,
                    "arabic": "ۗفَالْحُكْمُ",
                    "transliteration": "fal-ḥuk'mu",
                    "translation": "So the judgment",
                    "analysis_id": 24322
                },
                {
                    "position": 13,
                    "arabic": "لِلّٰهِ",
                    "transliteration": "lillahi",
                    "translation": "(is) with Allah",
                    "analysis_id": 6
                },
                {
                    "position": 14,
                    "arabic": "الْعَلِيِّ",
                    "transliteration": "l-ʿaliyi",
                    "translation": "the Most High",
                    "analysis_id": 24323
                },
                {
                    "position": 15,
                    "arabic": "الْكَبِيْرِ",
                    "transliteration": "l-kabīri",
                    "translation": "the Most Great",
                    "analysis_id": 24324
                }
            ]
        },
        {
            "aya_id": 4146,
            "aya_number": 13,
            "aya_text": "هُوَ الَّذِيْ يُرِيْكُمْ اٰيٰتِهٖ وَيُنَزِّلُ لَكُمْ مِّنَ السَّمَاۤءِ رِزْقًا ۗوَمَا يَتَذَكَّرُ اِلَّا مَنْ يُّنِيْبُ",
            "sura_id": 40,
            "juz_id": 24,
            "page_number": 468,
            "translation_aya_text": "Dialah yang memperlihatkan tanda-tanda (kekuasaan)-Nya kepadamu dan menurunkan rezeki dari langit untukmu. Dan tidak lain yang mendapat pelajaran hanyalah orang-orang yang kembali (kepada Allah).",
            "tafsir_jalalayn": "(Dialah yang memperlihatkan kepada kalian tanda-tanda-Nya) yang menunjukkan akan keesaan-Nya (dan menurunkan untuk kalian rezeki dari langit) berupa hujan. (Dan tiadalah mendapat pelajaran) yakni mengambil nasihat (kecuali orang-orang yang kembali kepada Allah) dari kemusyrikan.",
            "sajda": false,
            "transliteration": "Huwal lazee yureekum Aayaatihee wa yunazzilu lakum minas samaaa'i rizqaa; wa maa tatazakkaru illaa mai yuneeb",
            "tajweed_text": "هُوَ [h:153[ٱ]لَّذِى يُرِيكُمْ ءَايَ[n[ـٰ]تِه[n[ِۦ] وَيُنَزِّلُ لَك[w:1578[ُم م]ِّنَ [h:64[ٱ][l[ل]سَّم[o[َا]ٓءِ رِزْ[a:11802[قًاۚ و]َمَا يَتَذَكَّرُ إِلَّا م[a:11803[َن ي]ُن[p[ِي][q[ب]ُ",
            "words": [
                {
                    "position": 1,
                    "arabic": "هُوَ",
                    "transliteration": "huwa",
                    "translation": "He",
                    "analysis_id": 408
                },
                {
                    "position": 2,
                    "arabic": "الَّذِيْ",
                    "transliteration": "alladhī",
                    "translation": "(is) the One Who",
                    "analysis_id": 409
                },
                {
                    "position": 3,
                    "arabic": "يُرِيْكُمْ",
                    "transliteration": "yurīkum",
                    "translation": "shows you",
                    "analysis_id": 15803
                },
                {
                    "position": 4,
                    "arabic": "اٰيٰتِهٖ",
                    "transliteration": "āyātihi",
                    "translation": "His Signs",
                    "analysis_id": 21500
                },
                {
                    "position": 5,
                    "arabic": "وَيُنَزِّلُ",
                    "transliteration": "wayunazzilu",
                    "translation": "and sends down",
                    "analysis_id": 12407
                },
                {
                    "position": 6,
                    "arabic": "لَكُمْ",
                    "transliteration": "lakum",
                    "translation": "for you",
                    "analysis_id": 411
                },
                {
                    "position": 7,
                    "arabic": "مِّنَ",
                    "transliteration": "mina",
                    "translation": "from",
                    "analysis_id": 53
                },
                {
                    "position": 8,
                    "arabic": "السَّمَاۤءِ",
                    "transliteration": "l-samāi",
                    "translation": "the sky",
                    "analysis_id": 203
                },
                {
                    "position": 9,
                    "arabic": "رِزْقًا",
                    "transliteration": "riz'qan",
                    "translation": "provision",
                    "analysis_id": 14842
                },
                {
                    "position": 10,
                    "arabic": "ۗوَمَا",
                    "transliteration": "wamā",
                    "translation": "But (does) not",
                    "analysis_id": 1519
                },
                {
                    "position": 11,
                    "arabic": "يَتَذَكَّرُ",
                    "transliteration": "yatadhakkaru",
                    "translation": "take heed",
                    "analysis_id": 18795
                },
                {
                    "position": 12,
                    "arabic": "اِلَّا",
                    "transliteration": "illā",
                    "translation": "except",
                    "analysis_id": 1107
                },
                {
                    "position": 13,
                    "arabic": "مَنْ",
                    "transliteration": "man",
                    "translation": "(one) who",
                    "analysis_id": 88
                },
                {
                    "position": 14,
                    "arabic": "يُّنِيْبُ",
                    "transliteration": "yunību",
                    "translation": "turns",
                    "analysis_id": 24325
                }
            ]
        },
        {
            "aya_id": 4147,
            "aya_number": 14,
            "aya_text": "فَادْعُوا اللّٰهَ مُخْلِصِيْنَ لَهُ الدِّيْنَ وَلَوْ كَرِهَ الْكٰفِرُوْنَ",
            "sura_id": 40,
            "juz_id": 24,
            "page_number": 468,
            "translation_aya_text": "Maka sembahlah Allah dengan tulus ikhlas beragama kepada-Nya, meskipun orang-orang kafir tidak menyukai(nya).",
            "tafsir_jalalayn": "(Maka serulah Allah) sembahlah Dia (dengan memurnikan ibadah kepada-Nya) artinya, memurnikan agama dari kemusyrikan (meskipun orang-orang kafir tidak menyukainya) sekalipun mereka tidak menyukai keikhlasan kalian kepada-Nya.",
            "sajda": false,
            "transliteration": "Fad'ul laaha mukhliseena lahud deena wa law karihal kaafiroon",
            "tajweed_text": "فَ[h:9999[ٱ][q:11804[دْ]عُو[s[اْ] [h:11805[ٱ]للَّهَ مُخْلِصِينَ لَهُ [h:4649[ٱ][l[ل]دِّينَ وَلَوْ كَرِهَ [h:5556[ٱ]لْكَ[n[ـٰ]فِر[p[ُو]نَ",
            "words": [
                {
                    "position": 1,
                    "arabic": "فَادْعُوا",
                    "transliteration": "fa-id'ʿū",
                    "translation": "So invoke",
                    "analysis_id": 24326
                },
                {
                    "position": 2,
                    "arabic": "اللّٰهَ",
                    "transliteration": "l-laha",
                    "translation": "Allah",
                    "analysis_id": 98
                },
                {
                    "position": 3,
                    "arabic": "مُخْلِصِيْنَ",
                    "transliteration": "mukh'liṣīna",
                    "translation": "(being) sincere",
                    "analysis_id": 11163
                },
                {
                    "position": 4,
                    "arabic": "لَهُ",
                    "transliteration": "lahu",
                    "translation": "to Him",
                    "analysis_id": 2905
                },
                {
                    "position": 5,
                    "arabic": "الدِّيْنَ",
                    "transliteration": "l-dīna",
                    "translation": "(in) the religion",
                    "analysis_id": 1826
                },
                {
                    "position": 6,
                    "arabic": "وَلَوْ",
                    "transliteration": "walaw",
                    "translation": "even though",
                    "analysis_id": 7421
                },
                {
                    "position": 7,
                    "arabic": "كَرِهَ",
                    "transliteration": "kariha",
                    "translation": "dislike (it)",
                    "analysis_id": 12396
                },
                {
                    "position": 8,
                    "arabic": "الْكٰفِرُوْنَ",
                    "transliteration": "l-kāfirūna",
                    "translation": "the disbelievers",
                    "analysis_id": 8254
                }
            ]
        },
        {
            "aya_id": 4148,
            "aya_number": 15,
            "aya_text": "رَفِيْعُ الدَّرَجٰتِ ذُو الْعَرْشِۚ يُلْقِى الرُّوْحَ مِنْ اَمْرِهٖ عَلٰى مَنْ يَّشَاۤءُ مِنْ عِبَادِهٖ لِيُنْذِرَ يَوْمَ التَّلَاقِۙ",
            "sura_id": 40,
            "juz_id": 24,
            "page_number": 468,
            "translation_aya_text": "(Dialah) Yang Mahatinggi derajat-Nya, yang memiliki ’Arsy, yang menurunkan wahyu dengan perintah-Nya kepada siapa yang Dia kehendaki di antara hamba-hamba-Nya, agar memperingatkan (manusia) tentang hari pertemuan (hari Kiamat),",
            "tafsir_jalalayn": "(Dialah Yang Maha Tinggi derajat-Nya) maksudnya, Allah Maha Agung sifat-sifat-Nya, atau Dialah Yang mengangkat derajat orang-orang yang beriman di surga (Yang mempunyai Arasy) Yang menciptakannya (Yang menurunkan Ar-Ruuh) yakni wahyu (dari perintah-Nya) atau firman-nya (kepada siapa yang dikehendaki-Nya di antara hamba-hamba-Nya, supaya dia memperingatkan) maksudnya, orang yang menerima wahyu itu diperintahkan untuk menyampaikan wahyu-Nya kepada manusia (tentang hari pertemuan) dapat dibaca At-Talaaqi atau At-Talaaqiy dengan memakai huruf Ya. Yakni hari kiamat, karena pada hari itu penduduk langit dan penduduk bumi bertemu, dan bertemu pula antara Yang Disembah dan yang menyembah, sebagaimana dipertemukan pula antara orang yang aniaya dan orang yang dianiaya.",
            "sajda": false,
            "transliteration": "Rafee'ud darajaati zul 'Arshi yulqir rooha min amrihee 'alaa mai yashaaa'u min 'ibaadihee liyunzira yawmat talaaq",
            "tajweed_text": "رَفِيعُ [h:11806[ٱ][l[ل]دَّرَجَ[n[ـٰ]تِ ذُو [h:11807[ٱ]لْعَرْشِ يُلْقِى [h:11808[ٱ][l[ل]رُّوحَ مِنْ أَمْرِه[n[ِۦ] عَلَىٰ م[a:476[َن ي]َش[o[َا]ٓءُ مِنْ عِبَادِه[n[ِۦ] لِيُ[f:7947[نذ]ِرَ يَوْمَ [h:11809[ٱ][l[ل]تَّل[p[َا][q[ق]ِ",
            "words": [
                {
                    "position": 1,
                    "arabic": "رَفِيْعُ",
                    "transliteration": "rafīʿu",
                    "translation": "Possessor of the Highest Ranks",
                    "analysis_id": 24327
                },
                {
                    "position": 2,
                    "arabic": "الدَّرَجٰتِ",
                    "transliteration": "l-darajāti",
                    "translation": "Possessor of the Highest Ranks",
                    "analysis_id": 24328
                },
                {
                    "position": 3,
                    "arabic": "ذُو",
                    "transliteration": "dhū",
                    "translation": "Owner (of) the Throne",
                    "analysis_id": 4306
                },
                {
                    "position": 4,
                    "arabic": "الْعَرْشِۚ",
                    "transliteration": "l-ʿarshi",
                    "translation": "Owner (of) the Throne",
                    "analysis_id": 11347
                },
                {
                    "position": 5,
                    "arabic": "يُلْقِى",
                    "transliteration": "yul'qī",
                    "translation": "He places",
                    "analysis_id": 19818
                },
                {
                    "position": 6,
                    "arabic": "الرُّوْحَ",
                    "transliteration": "l-rūḥa",
                    "translation": "the inspiration",
                    "analysis_id": 24329
                },
                {
                    "position": 7,
                    "arabic": "مِنْ",
                    "transliteration": "min",
                    "translation": "of",
                    "analysis_id": 53
                },
                {
                    "position": 8,
                    "arabic": "اَمْرِهٖ",
                    "transliteration": "amrihi",
                    "translation": "His Command",
                    "analysis_id": 9472
                },
                {
                    "position": 9,
                    "arabic": "عَلٰى",
                    "transliteration": "ʿalā",
                    "translation": "upon",
                    "analysis_id": 59
                },
                {
                    "position": 10,
                    "arabic": "مَنْ",
                    "transliteration": "man",
                    "translation": "whom",
                    "analysis_id": 88
                },
                {
                    "position": 11,
                    "arabic": "يَّشَاۤءُ",
                    "transliteration": "yashāu",
                    "translation": "He wills",
                    "analysis_id": 4182
                },
                {
                    "position": 12,
                    "arabic": "مِنْ",
                    "transliteration": "min",
                    "translation": "of",
                    "analysis_id": 53
                },
                {
                    "position": 13,
                    "arabic": "عِبَادِهٖ",
                    "transliteration": "ʿibādihi",
                    "translation": "His slaves",
                    "analysis_id": 10123
                },
                {
                    "position": 14,
                    "arabic": "لِيُنْذِرَ",
                    "transliteration": "liyundhira",
                    "translation": "to warn",
                    "analysis_id": 17640
                },
                {
                    "position": 15,
                    "arabic": "يَوْمَ",
                    "transliteration": "yawma",
                    "translation": "(of the) Day",
                    "analysis_id": 12797
                },
                {
                    "position": 16,
                    "arabic": "التَّلَاقِۙ",
                    "transliteration": "l-talāqi",
                    "translation": "(of) the Meeting",
                    "analysis_id": 24330
                }
            ]
        },
        {
            "aya_id": 4149,
            "aya_number": 16,
            "aya_text": "يَوْمَ هُمْ بَارِزُوْنَ ۚ لَا يَخْفٰى عَلَى اللّٰهِ مِنْهُمْ شَيْءٌ ۗلِمَنِ الْمُلْكُ الْيَوْمَ ۗ لِلّٰهِ الْوَاحِدِ الْقَهَّارِ",
            "sura_id": 40,
            "juz_id": 24,
            "page_number": 468,
            "translation_aya_text": "(yaitu) pada hari (ketika) mereka keluar (dari kubur); tidak sesuatu pun keadaan mereka yang tersembunyi di sisi Allah. (Lalu Allah berfirman), “Milik siapakah kerajaan pada hari ini?” Milik Allah Yang Maha Esa, Maha Mengalahkan.",
            "tafsir_jalalayn": "(Yaitu hari ketika mereka keluar) dari kuburnya masing-masing (tiada suatu pun dari keadaan mereka yang tersembunyi bagi Allah berfirman, \"Kepunyaan siapakah kerajaan pada hari ini?\") Allah sendiri yang mengatakannya, kemudian Dia sendiri pula yang menjawabnya, yaitu, (\"Hanya kepunyaan Allah Yang Maha Esa lagi Maha Mengalahkan\") atas semua makhluk-Nya.",
            "sajda": false,
            "transliteration": "Yawma hum baarizoona laa yakhfaa 'alal laahi minhum shai; limanil mulkul Yawma lillaahil Waahidil Qahaar",
            "tajweed_text": "يَوْمَ ه[c:11810[ُم ب]َ[n[ـٰ]رِزُونَۖ لَا يَخْفَىٰ عَلَى [h:412[ٱ]للَّهِ مِنْهُمْ ش[u:11811[َىْءٌۚ ل]ِّمَنِ [h:11812[ٱ]لْمُلْكُ [h:11813[ٱ]لْيَوْمَۖ لِلَّهِ [h:7180[ٱ]لْو[n[َٲ]حِدِ [h:7181[ٱ]لْقَهّ[p[َا]رِ",
            "words": [
                {
                    "position": 1,
                    "arabic": "يَوْمَ",
                    "transliteration": "yawma",
                    "translation": "(The) Day",
                    "analysis_id": 12797
                },
                {
                    "position": 2,
                    "arabic": "هُمْ",
                    "transliteration": "hum",
                    "translation": "they",
                    "analysis_id": 95
                },
                {
                    "position": 3,
                    "arabic": "بَارِزُوْنَ",
                    "transliteration": "bārizūna",
                    "translation": "come forth",
                    "analysis_id": 24331
                },
                {
                    "position": 4,
                    "arabic": "ۚ",
                    "transliteration": "lā",
                    "translation": "not",
                    "analysis_id": 2198
                },
                {
                    "position": 5,
                    "arabic": "لَا",
                    "transliteration": "yakhfā",
                    "translation": "is hidden",
                    "analysis_id": 24332
                },
                {
                    "position": 6,
                    "arabic": "يَخْفٰى",
                    "transliteration": "ʿalā",
                    "translation": "from",
                    "analysis_id": 24333
                },
                {
                    "position": 7,
                    "arabic": "عَلَى",
                    "transliteration": "l-lahi",
                    "translation": "Allah",
                    "analysis_id": 1093
                },
                {
                    "position": 8,
                    "arabic": "اللّٰهِ",
                    "transliteration": "min'hum",
                    "translation": "about them",
                    "analysis_id": 24334
                },
                {
                    "position": 9,
                    "arabic": "مِنْهُمْ",
                    "transliteration": "shayon",
                    "translation": "anything",
                    "analysis_id": 2429
                },
                {
                    "position": 10,
                    "arabic": "شَيْءٌ",
                    "transliteration": "limani",
                    "translation": "For whom",
                    "analysis_id": 24335
                },
                {
                    "position": 11,
                    "arabic": "ۗلِمَنِ",
                    "transliteration": "l-mul'ku",
                    "translation": "(is) the Dominion",
                    "analysis_id": 23219
                },
                {
                    "position": 12,
                    "arabic": "الْمُلْكُ",
                    "transliteration": "l-yawma",
                    "translation": "this Day",
                    "analysis_id": 24336
                },
                {
                    "position": 13,
                    "arabic": "الْيَوْمَ",
                    "transliteration": "lillahi",
                    "translation": "For Allah",
                    "analysis_id": 24337
                },
                {
                    "position": 14,
                    "arabic": "ۗ",
                    "transliteration": "l-wāḥidi",
                    "translation": "the One",
                    "analysis_id": 24338
                },
                {
                    "position": 15,
                    "arabic": "لِلّٰهِ",
                    "transliteration": "l-qahāri",
                    "translation": "the Irresistible",
                    "analysis_id": 24339
                },
                {
                    "position": 16,
                    "arabic": "الْوَاحِدِ",
                    "transliteration": null,
                    "translation": "(16)",
                    "analysis_id": 15853
                },
                {
                    "position": 17,
                    "arabic": "الْقَهَّارِ",
                    "transliteration": "",
                    "translation": "",
                    "analysis_id": 15854
                }
            ]
        }
    ]
}